{"history": {"metadata": {"BOARDID": {"type": "string", "bytes": 12, "max_size": 0}, "TRADEDATE": {"type": "date", "bytes": 10, "max_size": 0}, "SHORTNAME": {"type": "string", "bytes": 189, "max_size": 0}, "SECID": {"type": "string", "bytes": 36, "max_size": 0}, "NUMTRADES": {"type": "double"}, "VALUE": {"type": "double"}, "OPEN": {"type": "double"}, "LOW": {"type": "double"}, "HIGH": {"type": "double"}, "LEGALCLOSEPRICE": {"type": "double"}, "WAPRICE": {"type": "double"}, "CLOSE": {"type": "double"}, "VOLUME": {"type": "double"}, "MARKETPRICE2": {"type": "double"}, "MARKETPRICE3": {"type": "double"}, "ADMITTEDQUOTE": {"type": "double"}, "MP2VALTRD": {"type": "double"}, "MARKETPRICE3TRADESVALUE": {"type": "double"}, "ADMITTEDVALUE": {"type": "double"}, "WAVAL": {"type": "double"}, "TRADINGSESSION": {"type": "int32"}, "CURRENCYID": {"type": "string", "bytes": 9, "max_size": 0}, "TRENDCLSPR": {"type": "double"}, "TRADE_SESSION_DATE": {"type": "date", "bytes": 10, "max_size": 0}}, "columns": ["BOARDID", "TRADEDATE", "SHORTNAME", "SECID", "NUMTRADES", "VALUE", "OPEN", "LOW", "HIGH", "LEGALCLOSEPRICE", "WAPRICE", "CLOSE", "VOLUME", "MARKETPRICE2", "MARKETPRICE3", "ADMITTEDQUOTE", "MP2VALTRD", "MARKETPRICE3TRADESVALUE", "ADMITTEDVALUE", "WAVAL", "TRADINGSESSION", "CURRENCYID", "TRENDCLSPR", "TRADE_SESSION_DATE"], "data": [["TQBR", "2024-09-27", "\u0417\u0418\u041b \u0430\u043e", "ZILL", 57, 684335, 3220, 3070, 3220, 3135, 3140, 3135, 218, 3140, 3140, null, 684335, 684335, null, 0, 3, "SUR", -1.57, null], ["TQBR", "2024-09-30", "\u0417\u0418\u041b \u0430\u043e", "ZILL", 71, 1147595, 3170, 3150, 3215, 3180, 3180, 3180, 361, 3180, 3180, null, 1147595, 1147595, null, 0, 3, "SUR", 1.44, null], ["TQBR", "2024-10-01", "\u0417\u0418\u041b \u0430\u043e", "ZILL", 18, 249655, 3165, 3155, 3190, 3165, 3160, 3190, 79, null, 3175, null, 0, 507715, null, 0, 3, "SUR", 0.31, null], ["TQBR", "2024-10-02", "\u0417\u0418\u041b \u0430\u043e", "ZILL", 20, 415115, 3145, 3140, 3185, 3140, 3145, 3140, 132, null, 3150, null, 0, 503610, null, 0, 3, "SUR", -1.57, null], ["TQBR", "2024-10-03", "\u0417\u0418\u041b \u0430\u043e", "ZILL", 12, 378285, 3140, 3125, 3155, 3125, 3125, 3125, 121, null, 3130, null, 0, 541565, null, 0, 3, "SUR", -0.48, null], ["TQBR", "2024-10-04", "\u0417\u0418\u041b \u0430\u043e", "ZILL", 30, 360230, 3120, 3090, 3130, 3090, 3105, 3090, 116, null, 3115, null, 0, 675905, null, 0, 3, "SUR", -1.12, null], ["TQBR", "2024-10-07", "\u0417\u0418\u041b \u0430\u043e", "ZILL", 35, 440315, 3075, 3070, 3115, 3075, 3100, 3075, 142, null, 3100, null, 0, 502115, null, 0, 3, "SUR", -0.49, null], ["TQBR", "2024-10-08", "\u0417\u0418\u041b \u0430\u043e", "ZILL", 30, 226835, 3075, 3050, 3110, 3075, 3065, 3075, 74, null, 3080, null, 0, 514555, null, 0, 3, "SUR", 0, null], ["TQBR", "2024-10-09", "\u0417\u0418\u041b \u0430\u043e", "ZILL", 24, 104445, 3060, 3055, 3095, 3080, 3070, 3080, 34, null, 3070, null, 0, 503845, null, 0, 3, "SUR", 0.16, null], ["TQBR", "2024-10-10", "\u0417\u0418\u041b \u0430\u043e", "ZILL", 34, 187740, 3065, 3055, 3105, 3100, 3080, 3100, 61, null, 3070, null, 0, 506740, null, 0, 3, "SUR", 0.65, null], ["TQBR", "2024-10-11", "\u0417\u0418\u041b \u0430\u043e", "ZILL", 20, 135490, 3075, 3065, 3105, 3065, 3080, 3065, 44, null, 3075, null, 0, 513250, null, 0, 3, "SUR", -1.13, null], ["TQBR", "2024-10-14", "\u0417\u0418\u041b \u0430\u043e", "ZILL", 40, 290975, 3065, 3010, 3095, 3085, 3065, 3085, 95, null, 3070, null, 0, 519195, null, 0, 3, "SUR", 0.65, null], ["TQBR", "2024-10-15", "\u0417\u0418\u041b \u0430\u043e", "ZILL", 19, 132515, 3050, 3050, 3100, 3095, 3080, 3095, 43, null, 3070, null, 0, 512655, null, 0, 3, "SUR", 0.32, null], ["TQBR", "2024-10-16", "\u0417\u0418\u041b \u0430\u043e", "ZILL", 41, 501150, 3085, 3050, 3170, 3090, 3095, 3090, 162, 3095, 3095, null, 501150, 501150, null, 0, 3, "SUR", -0.16, null], ["TQBR", "2024-10-17", "\u0417\u0418\u041b \u0430\u043e", "ZILL", 49, 1203245, 3065, 3025, 3090, 3070, 3045, 3070, 395, 3045, 3045, null, 1203245, 1203245, null, 0, 3, "SUR", -0.65, null], ["TQBR", "2024-10-18", "\u0417\u0418\u041b \u0430\u043e", "ZILL", 22, 185330, 3040, 3035, 3055, 3055, 3040, 3050, 61, null, 3050, null, 0, 537165, null, 0, 3, "SUR", -0.65, null], ["TQBR", "2024-10-21", "\u0417\u0418\u041b \u0430\u043e", "ZILL", 32, 217315, 3060, 3035, 3085, 3080, 3060, 3085, 71, null, 3055, null, 0, 687245, null, 0, 3, "SUR", 1.15, null], ["TQBR", "2024-10-22", "\u0417\u0418\u041b \u0430\u043e", "ZILL", 22, 187455, 3090, 3070, 3090, 3070, 3075, 3075, 61, null, 3060, null, 0, 502025, null, 0, 3, "SUR", -0.32, null], ["TQBR", "2024-10-23", "\u0417\u0418\u041b \u0430\u043e", "ZILL", 13, 138185, 3070, 3040, 3075, 3075, 3070, 3075, 45, null, 3070, null, 0, 500300, null, 0, 3, "SUR", 0, null], ["TQBR", "2024-10-24", "\u0417\u0418\u041b \u0430\u043e", "ZILL", 88, 1358275, 3060, 2900, 3125, 2980, 2985, 2980, 455, 2985, 2985, null, 1358275, 1358275, null, 0, 3, "SUR", -3.09, null], ["TQBR", "2024-10-25", "\u0417\u0418\u041b \u0430\u043e", "ZILL", 280, 4761240, 3000, 2900, 3200, 3070, 3060, 3070, 1557, 3060, 3060, null, 4761240, 4761240, null, 0, 3, "SUR", 3.02, null], ["TQBR", "2024-10-28", "\u0417\u0418\u041b \u0430\u043e", "ZILL", 82, 1605870, 3065, 2955, 3130, 2975, 3005, 2975, 534, 3005, 3005, null, 1605870, 1605870, null, 0, 3, "SUR", -3.09, null], ["TQBR", "2024-10-29", "\u0417\u0418\u041b \u0430\u043e", "ZILL", 60, 1025920, 3005, 2985, 3090, 3025, 3025, 3025, 339, 3025, 3025, null, 1025920, 1025920, null, 0, 3, "SUR", 1.68, null], ["TQBR", "2024-10-30", "\u0417\u0418\u041b \u0430\u043e", "ZILL", 125, 1783215, 3040, 2980, 3200, 3050, 3065, 3050, 582, 3065, 3065, null, 1783215, 1783215, null, 0, 3, "SUR", 0.83, null], ["TQBR", "2024-10-31", "\u0417\u0418\u041b \u0430\u043e", "ZILL", 32, 375285, 3050, 2985, 3050, 3040, 3000, 3040, 125, null, 3010, null, 0, 523930, null, 0, 3, "SUR", -0.33, null], ["TQBR", "2024-11-01", "\u0417\u0418\u041b \u0430\u043e", "ZILL", 22, 134945, 2985, 2930, 3030, 3020, 3000, 3020, 45, null, 3000, null, 0, 501080, null, 0, 3, "SUR", -0.66, null], ["TQBR", "2024-11-02", "\u0417\u0418\u041b \u0430\u043e", "ZILL", 23, 359115, 2930, 2925, 3040, 2985, 2995, 2980, 120, null, 2995, null, 0, 500130, null, 0, 3, "SUR", -1.32, null], ["TQBR", "2024-11-05", "\u0417\u0418\u041b \u0430\u043e", "ZILL", 35, 606345, 2945, 2945, 3040, 3000, 3000, 3000, 202, 3000, 3000, null, 606345, 606345, null, 0, 3, "SUR", 0.67, null], ["TQBR", "2024-11-06", "\u0417\u0418\u041b \u0430\u043e", "ZILL", 60, 1097115, 3055, 3000, 3115, 3085, 3065, 3060, 358, 3065, 3065, null, 1097115, 1097115, null, 0, 3, "SUR", 2, null], ["TQBR", "2024-11-07", "\u0417\u0418\u041b \u0430\u043e", "ZILL", 38, 850535, 3045, 3045, 3120, 3080, 3080, 3080, 276, 3080, 3080, null, 850535, 850535, null, 0, 3, "SUR", 0.65, null], ["TQBR", "2024-11-08", "\u0417\u0418\u041b \u0430\u043e", "ZILL", 10, 123010, 3075, 3060, 3095, 3080, 3075, 3080, 40, null, 3085, null, 0, 558375, null, 0, 3, "SUR", 0, null], ["TQBR", "2024-11-11", "\u0417\u0418\u041b \u0430\u043e", "ZILL", 25, 202495, 3060, 3060, 3095, 3085, 3070, 3095, 66, null, 3080, null, 0, 532640, null, 0, 3, "SUR", 0.49, null], ["TQBR", "2024-11-12", "\u0417\u0418\u041b \u0430\u043e", "ZILL", 44, 774425, 3090, 3090, 3160, 3125, 3135, 3125, 247, 3135, 3135, null, 774425, 774425, null, 0, 3, "SUR", 0.97, null], ["TQBR", "2024-11-13", "\u0417\u0418\u041b \u0430\u043e", "ZILL", 35, 321670, 3100, 3100, 3190, 3120, 3155, 3120, 102, null, 3140, null, 0, 515265, null, 0, 3, "SUR", -0.16, null], ["TQBR", "2024-11-14", "\u0417\u0418\u041b \u0430\u043e", "ZILL", 52, 1262750, 3150, 3150, 3200, 3150, 3175, 3150, 398, 3175, 3175, null, 1262750, 1262750, null, 0, 3, "SUR", 0.96, null], ["TQBR", "2024-11-15", "\u0417\u0418\u041b \u0430\u043e", "ZILL", 21, 177290, 3150, 3085, 3160, 3105, 3110, 3105, 57, null, 3140, null, 0, 539945, null, 0, 3, "SUR", -1.43, null], ["TQBR", "2024-11-18", "\u0417\u0418\u041b \u0430\u043e", "ZILL", 88, 1429540, 3150, 2950, 3150, 3010, 3005, 3010, 476, 3005, 3005, null, 1429540, 1429540, null, 0, 3, "SUR", -3.06, null], ["TQBR", "2024-11-19", "\u0417\u0418\u041b \u0430\u043e", "ZILL", 63, 837190, 3010, 2950, 3050, 2975, 2990, 2955, 280, 2990, 2990, null, 837190, 837190, null, 0, 3, "SUR", -1.83, null], ["TQBR", "2024-11-20", "\u0417\u0418\u041b \u0430\u043e", "ZILL", 25, 1398545, 3005, 2960, 3005, 2960, 2965, 2960, 472, 2965, 2965, null, 1398545, 1398545, null, 0, 3, "SUR", 0.17, null], ["TQBR", "2024-11-21", "\u0417\u0418\u041b \u0430\u043e", "ZILL", 112, 3930440, 2985, 2985, 3140, 3040, 3040, 3040, 1292, 3040, 3040, null, 3930440, 3930440, null, 0, 3, "SUR", 2.7, null], ["TQBR", "2024-11-22", "\u0417\u0418\u041b \u0430\u043e", "ZILL", 34, 690395, 3060, 3000, 3060, 3000, 3030, 3000, 228, 3030, 3030, null, 690395, 690395, null, 0, 3, "SUR", -1.32, null], ["TQBR", "2024-11-25", "\u0417\u0418\u041b \u0430\u043e", "ZILL", 56, 882595, 3040, 2965, 3050, 3050, 3025, 3050, 292, 3025, 3025, null, 882595, 882595, null, 0, 3, "SUR", 1.67, null], ["TQBR", "2024-11-26", "\u0417\u0418\u041b \u0430\u043e", "ZILL", 72, 2180105, 3040, 2980, 3100, 3050, 3040, 3050, 717, 3040, 3040, null, 2180105, 2180105, null, 0, 3, "SUR", 0, null], ["TQBR", "2024-11-27", "\u0417\u0418\u041b \u0430\u043e", "ZILL", 90, 2054825, 3015, 2910, 3050, 2925, 2980, 2925, 689, 2980, 2980, null, 2054825, 2054825, null, 0, 3, "SUR", -4.1, null], ["TQBR", "2024-11-28", "\u0417\u0418\u041b \u0430\u043e", "ZILL", 38, 537685, 2995, 2950, 3050, 2975, 3005, 2975, 179, 3005, 3005, null, 537685, 537685, null, 0, 3, "SUR", 1.71, null], ["TQBR", "2024-11-29", "\u0417\u0418\u041b \u0430\u043e", "ZILL", 15, 215685, 2990, 2990, 3010, 2990, 2995, 2990, 72, null, 2985, null, 0, 507235, null, 0, 3, "SUR", 0.5, null], ["TQBR", "2024-12-02", "\u0417\u0418\u041b \u0430\u043e", "ZILL", 44, 518965, 3020, 2945, 3020, 3015, 2985, 3015, 174, 2985, 2985, null, 518965, 518965, null, 0, 3, "SUR", 0.84, null], ["TQBR", "2024-12-03", "\u0417\u0418\u041b \u0430\u043e", "ZILL", 536, 12922900, 2995, 2995, 3665, 3545, 3370, 3545, 3832, 3370, 3370, null, 12922900, 12922900, null, 0, 3, "SUR", 17.58, null], ["TQBR", "2024-12-04", "\u0417\u0418\u041b \u0430\u043e", "ZILL", 692, 10889110, 3195, 3195, 3575, 3255, 3375, 3255, 3228, 3375, 3375, null, 10889110, 10889110, null, 0, 3, "SUR", -8.18, null], ["TQBR", "2024-12-05", "\u0417\u0418\u041b \u0430\u043e", "ZILL", 306, 5201880, 3300, 3030, 3340, 3150, 3145, 3150, 1655, 3145, 3145, null, 5201880, 5201880, null, 0, 3, "SUR", -3.23, null], ["TQBR", "2024-12-06", "\u0417\u0418\u041b \u0430\u043e", "ZILL", 147, 1441420, 3195, 3100, 3270, 3115, 3180, 3115, 453, 3180, 3180, null, 1441420, 1441420, null, 0, 3, "SUR", -1.11, null], ["TQBR", "2024-12-09", "\u0417\u0418\u041b \u0430\u043e", "ZILL", 39, 324990, 3160, 3060, 3170, 3070, 3095, 3095, 105, null, 3100, null, 0, 502175, null, 0, 3, "SUR", -0.64, null], ["TQBR", "2024-12-10", "\u0417\u0418\u041b \u0430\u043e", "ZILL", 63, 658825, 3110, 3030, 3120, 3040, 3065, 3040, 215, 3065, 3065, null, 658825, 658825, null, 0, 3, "SUR", -1.78, null], ["TQBR", "2024-12-11", "\u0417\u0418\u041b \u0430\u043e", "ZILL", 75, 1411435, 3040, 3005, 3090, 3015, 3040, 3015, 464, 3040, 3040, null, 1411435, 1411435, null, 0, 3, "SUR", -0.82, null], ["TQBR", "2024-12-12", "\u0417\u0418\u041b \u0430\u043e", "ZILL", 153, 2941805, 3030, 3015, 3240, 3040, 3115, 3040, 945, 3115, 3115, null, 2941805, 2941805, null, 0, 3, "SUR", 0.83, null], ["TQBR", "2024-12-13", "\u0417\u0418\u041b \u0430\u043e", "ZILL", 73, 2273075, 3035, 3010, 3060, 3015, 3025, 3015, 752, 3025, 3025, null, 2273075, 2273075, null, 0, 3, "SUR", -0.82, null], ["TQBR", "2024-12-16", "\u0417\u0418\u041b \u0430\u043e", "ZILL", 37, 2498605, 3010, 3010, 3055, 3015, 3020, 3015, 827, 3020, 3020, null, 2498605, 2498605, null, 0, 3, "SUR", 0, null], ["TQBR", "2024-12-17", "\u0417\u0418\u041b \u0430\u043e", "ZILL", 29, 623055, 3020, 3015, 3040, 3040, 3025, 3040, 206, 3025, 3025, null, 623055, 623055, null, 0, 3, "SUR", 0.83, null], ["TQBR", "2024-12-18", "\u0417\u0418\u041b \u0430\u043e", "ZILL", 8, 42485, 3015, 3015, 3045, 3045, 3035, 3045, 14, 3025, 3025, null, 665540, 553795, null, 0, 3, "SUR", 0.16, null], ["TQBR", "2024-12-19", "\u0417\u0418\u041b \u0430\u043e", "ZILL", 92, 3984375, 3035, 3020, 3185, 3100, 3130, 3125, 1273, 3130, 3130, null, 3984375, 3984375, null, 0, 3, "SUR", 2.63, null], ["TQBR", "2024-12-20", "\u0417\u0418\u041b \u0430\u043e", "ZILL", 233, 3740430, 3125, 3035, 3205, 3125, 3115, 3125, 1200, 3115, 3115, null, 3740430, 3740430, null, 0, 3, "SUR", 0, null], ["TQBR", "2024-12-23", "\u0417\u0418\u041b \u0430\u043e", "ZILL", 208, 2458830, 3145, 3145, 3335, 3210, 3220, 3210, 764, 3220, 3220, null, 2458830, 2458830, null, 0, 3, "SUR", 2.72, null], ["TQBR", "2024-12-24", "\u0417\u0418\u041b \u0430\u043e", "ZILL", 78, 1724735, 3280, 3070, 3295, 3240, 3190, 3240, 541, 3190, 3190, null, 1724735, 1724735, null, 0, 3, "SUR", 0.93, null], ["TQBR", "2024-12-25", "\u0417\u0418\u041b \u0430\u043e", "ZILL", 98, 2566480, 3240, 3105, 3330, 3330, 3235, 3330, 793, 3235, 3235, null, 2566480, 2566480, null, 0, 3, "SUR", 2.78, null], ["TQBR", "2024-12-26", "\u0417\u0418\u041b \u0430\u043e", "ZILL", 74, 1148965, 3330, 3230, 3390, 3250, 3285, 3250, 350, 3285, 3285, null, 1148965, 1148965, null, 0, 3, "SUR", -2.4, null], ["TQBR", "2024-12-27", "\u0417\u0418\u041b \u0430\u043e", "ZILL", 38, 301675, 3250, 3180, 3250, 3180, 3210, 3180, 94, null, 3230, null, 0, 500515, null, 0, 3, "SUR", -2.15, null], ["TQBR", "2024-12-28", "\u0417\u0418\u041b \u0430\u043e", "ZILL", 45, 1233915, 3240, 3175, 3265, 3250, 3205, 3250, 385, 3205, 3205, null, 1233915, 1233915, null, 0, 3, "SUR", 2.2, null], ["TQBR", "2024-12-30", "\u0417\u0418\u041b \u0430\u043e", "ZILL", 82, 2077060, 3245, 3220, 3315, 3245, 3265, 3245, 636, 3265, 3265, null, 2077060, 2077060, null, 0, 3, "SUR", -0.15, null], ["TQBR", "2025-01-03", "\u0417\u0418\u041b \u0430\u043e", "ZILL", 92, 1190065, 3255, 3225, 3485, 3315, 3345, 3315, 356, 3345, 3345, null, 1190065, 1190065, null, 0, 3, "SUR", 2.16, null]]}, "history.cursor": {"metadata": {"INDEX": {"type": "int64"}, "TOTAL": {"type": "int64"}, "PAGESIZE": {"type": "int64"}}, "columns": ["INDEX", "TOTAL", "PAGESIZE"], "data": [[0, 69, 100]]}}